longscurvefitting/__init__.py
longscurvefitting/_helpers.py
longscurvefitting/longscurvefitting.py
longscurvefitting/models.py
longscurvefitting/scipycurvefitm.py
adaptive_curvefitting-0.1.5.dist-info/LICENSE
adaptive_curvefitting-0.1.5.dist-info/METADATA
adaptive_curvefitting-0.1.5.dist-info/WHEEL
adaptive_curvefitting-0.1.5.dist-info/top_level.txt
adaptive_curvefitting-0.1.5.dist-info/RECORD
