Metadata-Version: 2.1
Name: adaptive-curvefitting
Version: 0.1.5
Summary: A tool for adaptive selection of curve-fitting models.
Home-page: https://github.com/longavailable/adaptive-curvefitting
Author: Xiaolong "Bruce" Liu, Meixiu Yu
Author-email: liuxiaolong125@gmail.com, meixiuyu@hhu.edu.cn
License: UNKNOWN
Platform: UNKNOWN
Classifier: Programming Language :: Python :: 3
Classifier: License :: OSI Approved :: MIT License
Classifier: Operating System :: OS Independent
Requires-Python: >=3.6
License-File: LICENSE
Requires-Dist: pandas
Requires-Dist: matplotlib
Requires-Dist: scipy
